{
  "servicios": [
    {
      "id": 1,
      "categoria": "polarizado",
      "nombre": "Polarizado Premium - Auto ($85.000)",
      "descripcion": "Lámina Premium Nano Carbono. Protección UV, reducción de calor y mayor privacidad.",
      "precio": 85000,
      "precioNota": "lámina premium · +$30.000 despolarizado",
      "vehiculos": ["Auto"],
      "badge": "badge-polarizado",
      "badgeLabel": "Polarizado"
    },
    {
      "id": 2,
      "categoria": "polarizado",
      "nombre": "Polarizado Premium - SUV ($95.000)",
      "descripcion": "Lámina Premium Nano Carbono para SUV. Protección UV, reducción de calor y mayor privacidad.",
      "precio": 95000,
      "precioNota": "lámina premium · +$35.000 despolarizado",
      "vehiculos": ["SUV"],
      "badge": "badge-polarizado",
      "badgeLabel": "Polarizado"
    },
    {
      "id": 3,
      "categoria": "polarizado",
      "nombre": "Polarizado Premium - Camioneta ($95.000 a $115.000)",
      "descripcion": "Lámina Premium Nano Carbono para camionetas y furgones vidriados. Precio según cantidad de vidrios.",
      "precio": 95000,
      "precioNota": "desde $95.000 hasta $115.000 · despolarizado desde $40.000",
      "vehiculos": ["Camioneta"],
      "badge": "badge-polarizado",
      "badgeLabel": "Polarizado"
    },
    {
      "id": 4,
      "categoria": "abrillantado",
      "nombre": "Abrillantado Común (1 Paso) - Auto ($70.000)",
      "descripcion": "1 paso + sellado acrílico. Descontaminación incluida.",
      "precio": 70000,
      "precioNota": "por auto",
      "vehiculos": ["Auto"],
      "badge": "badge-abrillantado",
      "badgeLabel": "Abrillantado"
    },
    {
      "id": 5,
      "categoria": "abrillantado",
      "nombre": "Abrillantado Común (1 Paso) - SUV ($85.000)",
      "descripcion": "1 paso + sellado acrílico. Descontaminación incluida.",
      "precio": 85000,
      "precioNota": "por vehículo",
      "vehiculos": ["SUV"],
      "badge": "badge-abrillantado",
      "badgeLabel": "Abrillantado"
    },
    {
      "id": 6,
      "categoria": "abrillantado",
      "nombre": "Abrillantado Común (1 Paso) - Camioneta ($100.000)",
      "descripcion": "1 paso + sellado acrílico. Descontaminación incluida.",
      "precio": 100000,
      "precioNota": "por vehículo",
      "vehiculos": ["Camioneta"],
      "badge": "badge-abrillantado",
      "badgeLabel": "Abrillantado"
    },
    {
      "id": 7,
      "categoria": "abrillantado",
      "nombre": "Abrillantado Profundo (2 Pasos) - Auto ($90.000)",
      "descripcion": "2 pasos + sellado acrílico. Mayor brillo, más protección y mayor durabilidad. Descontaminación incluida.",
      "precio": 90000,
      "precioNota": "por auto",
      "vehiculos": ["Auto"],
      "badge": "badge-abrillantado",
      "badgeLabel": "Abrillantado"
    },
    {
      "id": 8,
      "categoria": "abrillantado",
      "nombre": "Abrillantado Profundo (2 Pasos) - SUV ($100.000)",
      "descripcion": "2 pasos + sellado acrílico. Mayor brillo, más protección y mayor durabilidad. Descontaminación incluida.",
      "precio": 100000,
      "precioNota": "por vehículo",
      "vehiculos": ["SUV"],
      "badge": "badge-abrillantado",
      "badgeLabel": "Abrillantado"
    },
    {
      "id": 9,
      "categoria": "abrillantado",
      "nombre": "Abrillantado Profundo (2 Pasos) - Camioneta ($130.000)",
      "descripcion": "2 pasos + sellado acrílico. Mayor brillo, más protección y mayor durabilidad. Descontaminación incluida.",
      "precio": 130000,
      "precioNota": "por vehículo",
      "vehiculos": ["Camioneta"],
      "badge": "badge-abrillantado",
      "badgeLabel": "Abrillantado"
    },
    {
      "id": 10,
      "categoria": "estetica",
      "nombre": "Pulido de Ópticas (1 Óptica - $25.000)",
      "descripcion": "Recuperamos la transparencia de tu óptica. Incluye sellado protector.",
      "precio": 25000,
      "precioNota": "por óptica",
      "vehiculos": ["Auto", "SUV", "Camioneta"],
      "badge": "badge-estetica",
      "badgeLabel": "Estética"
    },
    {
      "id": 11,
      "categoria": "estetica",
      "nombre": "Pulido de Ópticas (2 Ópticas - $40.000)",
      "descripcion": "Recuperamos la transparencia de ambas ópticas delanteras. Incluye sellado protector.",
      "precio": 40000,
      "precioNota": "par de ópticas",
      "vehiculos": ["Auto", "SUV", "Camioneta"],
      "badge": "badge-estetica",
      "badgeLabel": "Estética"
    },
    {
      "id": 12,
      "categoria": "estetica",
      "nombre": "Limpieza de Tapizados - Auto ($70.000)",
      "descripcion": "Limpieza profunda de asientos, alfombras y techo. Eliminación de olores y manchas.",
      "precio": 70000,
      "precioNota": "por auto",
      "vehiculos": ["Auto"],
      "badge": "badge-estetica",
      "badgeLabel": "Estética"
    },
    {
      "id": 13,
      "categoria": "estetica",
      "nombre": "Limpieza de Tapizados - SUV ($85.000)",
      "descripcion": "Limpieza profunda de asientos, alfombras y techo. Eliminación de olores y manchas.",
      "precio": 85000,
      "precioNota": "por vehículo",
      "vehiculos": ["SUV"],
      "badge": "badge-estetica",
      "badgeLabel": "Estética"
    },
    {
      "id": 14,
      "categoria": "estetica",
      "nombre": "Limpieza de Tapizados - Camioneta ($100.000)",
      "descripcion": "Limpieza profunda de asientos, alfombras y techo. Eliminación de olores y manchas.",
      "precio": 100000,
      "precioNota": "por vehículo",
      "vehiculos": ["Camioneta"],
      "badge": "badge-estetica",
      "badgeLabel": "Estética"
    },
    {
      "id": 15,
      "categoria": "estetica",
      "nombre": "Limpieza de Motor Básica - Auto ($25.000)",
      "descripcion": "Limpieza básica del compartimento del motor.",
      "precio": 25000,
      "precioNota": "por auto",
      "vehiculos": ["Auto"],
      "badge": "badge-estetica",
      "badgeLabel": "Estética"
    },
    {
      "id": 16,
      "categoria": "estetica",
      "nombre": "Limpieza de Motor Básica - SUV ($30.000)",
      "descripcion": "Limpieza básica del compartimento del motor.",
      "precio": 30000,
      "precioNota": "por vehículo",
      "vehiculos": ["SUV"],
      "badge": "badge-estetica",
      "badgeLabel": "Estética"
    },
    {
      "id": 17,
      "categoria": "estetica",
      "nombre": "Limpieza de Motor Básica - Camioneta ($35.000)",
      "descripcion": "Limpieza básica del compartimento del motor.",
      "precio": 35000,
      "precioNota": "por vehículo",
      "vehiculos": ["Camioneta"],
      "badge": "badge-estetica",
      "badgeLabel": "Estética"
    },
    {
      "id": 18,
      "categoria": "estetica",
      "nombre": "Limpieza de Motor Premium - Auto ($45.000)",
      "descripcion": "Limpieza detallada + terminación estética del motor.",
      "precio": 45000,
      "precioNota": "por auto",
      "vehiculos": ["Auto"],
      "badge": "badge-estetica",
      "badgeLabel": "Estética"
    },
    {
      "id": 19,
      "categoria": "estetica",
      "nombre": "Limpieza de Motor Premium - SUV ($50.000)",
      "descripcion": "Limpieza detallada + terminación estética del motor.",
      "precio": 50000,
      "precioNota": "por vehículo",
      "vehiculos": ["SUV"],
      "badge": "badge-estetica",
      "badgeLabel": "Estética"
    },
    {
      "id": 20,
      "categoria": "estetica",
      "nombre": "Limpieza de Motor Premium - Camioneta ($60.000)",
      "descripcion": "Limpieza detallada + terminación estética del motor.",
      "precio": 60000,
      "precioNota": "por vehículo",
      "vehiculos": ["Camioneta"],
      "badge": "badge-estetica",
      "badgeLabel": "Estética"
    },
    {
      "id": 21,
      "categoria": "lavado",
      "nombre": "Lavado Estético Moto 110cc ($15.000)",
      "descripcion": "Lavado estético completo para motos de 110cc.",
      "precio": 15000,
      "precioNota": "por moto",
      "vehiculos": ["Moto"],
      "badge": "badge-lavado",
      "badgeLabel": "Lavado"
    },
    {
      "id": 22,
      "categoria": "lavado",
      "nombre": "Lavado Estético Moto 150cc ($25.000)",
      "descripcion": "Lavado estético completo para motos de 150cc.",
      "precio": 25000,
      "precioNota": "por moto",
      "vehiculos": ["Moto"],
      "badge": "badge-lavado",
      "badgeLabel": "Lavado"
    },
    {
      "id": 23,
      "categoria": "lavado",
      "nombre": "Lavado Estético Moto 250cc ($30.000)",
      "descripcion": "Lavado estético completo para motos de 250cc.",
      "precio": 30000,
      "precioNota": "por moto",
      "vehiculos": ["Moto"],
      "badge": "badge-lavado",
      "badgeLabel": "Lavado"
    },
    {
      "id": 24,
      "categoria": "lavado",
      "nombre": "Lavado Estético Moto 400cc ($35.000)",
      "descripcion": "Lavado estético completo para motos de 400cc.",
      "precio": 35000,
      "precioNota": "por moto",
      "vehiculos": ["Moto"],
      "badge": "badge-lavado",
      "badgeLabel": "Lavado"
    },
    {
      "id": 25,
      "categoria": "lavado",
      "nombre": "Lavado Estético Moto 600cc ($45.000)",
      "descripcion": "Lavado estético completo para motos de 600cc.",
      "precio": 45000,
      "precioNota": "por moto",
      "vehiculos": ["Moto"],
      "badge": "badge-lavado",
      "badgeLabel": "Lavado"
    },
    {
      "id": 26,
      "categoria": "lavado",
      "nombre": "Lavado Profundo Moto 110cc ($25.000)",
      "descripcion": "Lavado profundo con limpieza detallada para motos de 110cc.",
      "precio": 25000,
      "precioNota": "por moto",
      "vehiculos": ["Moto"],
      "badge": "badge-lavado",
      "badgeLabel": "Lavado"
    },
    {
      "id": 27,
      "categoria": "lavado",
      "nombre": "Lavado Profundo Moto 150cc ($50.000)",
      "descripcion": "Lavado profundo con limpieza detallada para motos de 150cc.",
      "precio": 50000,
      "precioNota": "por moto",
      "vehiculos": ["Moto"],
      "badge": "badge-lavado",
      "badgeLabel": "Lavado"
    },
    {
      "id": 28,
      "categoria": "lavado",
      "nombre": "Lavado Profundo Moto 250cc ($65.000)",
      "descripcion": "Lavado profundo con limpieza detallada para motos de 250cc.",
      "precio": 65000,
      "precioNota": "por moto",
      "vehiculos": ["Moto"],
      "badge": "badge-lavado",
      "badgeLabel": "Lavado"
    },
    {
      "id": 29,
      "categoria": "lavado",
      "nombre": "Lavado Profundo Moto 400cc ($75.000)",
      "descripcion": "Lavado profundo con limpieza detallada para motos de 400cc.",
      "precio": 75000,
      "precioNota": "por moto",
      "vehiculos": ["Moto"],
      "badge": "badge-lavado",
      "badgeLabel": "Lavado"
    },
    {
      "id": 30,
      "categoria": "lavado",
      "nombre": "Lavado Profundo Moto 600cc ($85.000)",
      "descripcion": "Lavado profundo con limpieza detallada para motos de 600cc.",
      "precio": 85000,
      "precioNota": "por moto",
      "vehiculos": ["Moto"],
      "badge": "badge-lavado",
      "badgeLabel": "Lavado"
    },
    {
      "id": 31,
      "categoria": "detailing",
      "nombre": "Limpieza y Nutrición de Plásticos Interiores",
      "descripcion": "Limpieza profunda y nutrición de todos los plásticos del interior del vehículo.",
      "precio": 0,
      "precioNota": "consultá precio",
      "vehiculos": ["Auto", "SUV", "Camioneta"],
      "badge": "badge-detailing",
      "badgeLabel": "Detailing"
    },
    {
      "id": 32,
      "categoria": "detailing",
      "nombre": "Limpieza y Nutrición de Plásticos Exteriores",
      "descripcion": "Limpieza y nutrición de paragolpes, molduras y plásticos exteriores.",
      "precio": 0,
      "precioNota": "consultá precio",
      "vehiculos": ["Auto", "SUV", "Camioneta"],
      "badge": "badge-detailing",
      "badgeLabel": "Detailing"
    },
    {
      "id": 33,
      "categoria": "detailing",
      "nombre": "Limpieza de Chasis",
      "descripcion": "Limpieza profunda del chasis y zona inferior del vehículo.",
      "precio": 0,
      "precioNota": "consultá precio",
      "vehiculos": ["Auto", "SUV", "Camioneta"],
      "badge": "badge-detailing",
      "badgeLabel": "Detailing"
    },
    {
      "id": 34,
      "categoria": "detailing",
      "nombre": "Detailing Completo de Moto",
      "descripcion": "Detailing completo y profesional para motos. Cada pieza tratada en detalle.",
      "precio": 0,
      "precioNota": "consultá precio",
      "vehiculos": ["Moto"],
      "badge": "badge-detailing",
      "badgeLabel": "Detailing"
    }
  ]
}